empower_personal_capital-0.0.2.dist-info/licenses/LICENSE
personalcapital/__init__.py
personalcapital/personalcapital.py
empower_personal_capital-0.0.2.dist-info/METADATA
empower_personal_capital-0.0.2.dist-info/WHEEL
empower_personal_capital-0.0.2.dist-info/top_level.txt
empower_personal_capital-0.0.2.dist-info/RECORD
