Metadata-Version: 2.4
Name: empower_personal_capital
Version: 0.0.2
Summary: A Python library for interacting with the Personal Capital API. Easily log in, handle two-factor authentication, and fetch financial data like account details and net worth. Simplify automation and data retrieval from your Personal Capital account with this lightweight and user-friendly package.
Home-page: https://github.com/haochi/personalcapital
Download-URL: https://github.com/haochi/personalcapital/tarball/1.0.1
Author: chocotonic
Author-email: pypi@ihaochi.com
License-Expression: MIT
Project-URL: Homepage, https://github.com/ChocoTonic/personalcapital-py
Project-URL: Issues, https://github.com/ChocoTonic/personalcapital-py/issues
Classifier: Programming Language :: Python :: 3
Classifier: Operating System :: OS Independent
Requires-Python: >=3.8
License-File: LICENSE
Dynamic: author-email
Dynamic: download-url
Dynamic: home-page
Dynamic: license-file
